information_resource_registry/_version.py
information_resource_registry/datamodel/__init__.py
information_resource_registry/datamodel/information_resource_registry.py
information_resource_registry/datamodel/pydanticmodel_v2.py
information_resource_registry/schema/information_resource_registry.yaml
information_resource_registry/translator_dataflow/Automat_infores.py
information_resource_registry/translator_dataflow/README
information_resource_registry/translator_dataflow/__init__.py
information_resource_registry/translator_dataflow/add_consume_info.py
information_resource_registry/translator_dataflow/aragorn_kps.py
information_resource_registry/translator_dataflow/arax_kps.py
information_resource_registry/translator_dataflow/bte_sp.py
information_resource_registry/translator_dataflow/data/aragorn_to_kps.json
information_resource_registry/translator_dataflow/data/arax_infores_list.json
information_resource_registry/translator_dataflow/data/ars_to_aras.json
information_resource_registry/translator_dataflow/data/bte_to_kps.json
information_resource_registry/translator_dataflow/data/clinicaldata_infores_list.json
information_resource_registry/translator_dataflow/data/consume_info.csv
information_resource_registry/translator_dataflow/data/data_flow_diagram.png
information_resource_registry/translator_dataflow/data/geneticskp_resources.json
information_resource_registry/translator_dataflow/data/kps_to_apis.json
information_resource_registry/translator_dataflow/data/molepro_resources.json
information_resource_registry/translator_dataflow/data/rtx-kg2.json
information_resource_registry/translator_dataflow/data/sankey_diagram.png
information_resource_registry/translator_dataflow/data/sp_to_kps.json
information_resource_registry/translator_dataflow/data/unsecret.json
information_resource_registry/translator_dataflow/extract_consume_info.py
information_resource_registry/translator_dataflow/generate_sankey.py
information_resource_registry-1.1.5.dist-info/METADATA
information_resource_registry-1.1.5.dist-info/WHEEL
information_resource_registry-1.1.5.dist-info/entry_points.txt
information_resource_registry-1.1.5.dist-info/licenses/LICENSE
information_resource_registry-1.1.5.dist-info/RECORD
