Metadata-Version: 2.4
Name: information-resource-registry
Version: 1.1.5
Summary: A registry of information resources used in NCATS Data Translator
License: MIT
License-File: LICENSE
Author: Sierra Moxon
Author-email: smoxon@lbl.gov
Requires-Python: >=3.10,<4.0
Classifier: License :: OSI Approved :: MIT License
Classifier: Programming Language :: Python :: 3
Classifier: Programming Language :: Python :: 3.10
Classifier: Programming Language :: Python :: 3.11
Classifier: Programming Language :: Python :: 3.12
Classifier: Programming Language :: Python :: 3.13
Classifier: Programming Language :: Python :: 3.14
Provides-Extra: docs
Requires-Dist: beautifulsoup4 (>=4.0.0)
Requires-Dist: curies (>=0.7.4,<0.8.0)
Requires-Dist: kaleido (==0.2.1)
Requires-Dist: linkml (>=1.8.5,<2.0.0)
Requires-Dist: pandas (>=2.2.3,<3.0.0)
Requires-Dist: plotly (>=5.24.1,<6.0.0)
Requires-Dist: prefixmaps (>=0.2.0,<0.3.0)
Requires-Dist: pytest (>=7.3.1,<8.0.0)
Requires-Dist: pyyaml (>=6.0.1,<7.0.0)
Requires-Dist: stringcase (>=1.2.0,<2.0.0)
Requires-Dist: tqdm (>=4.66.6,<5.0.0)
Requires-Dist: yamllint (>=1.35.1,<2.0.0)
